kumparanian/__init__.py
kumparanian/__main__.py
kumparanian/cli.py
kumparanian/ds/__init__.py
kumparanian/ds/help_text.py
kumparanian/ds/model.py
kumparanian-1.2.1.dist-info/LICENSE
kumparanian-1.2.1.dist-info/METADATA
kumparanian-1.2.1.dist-info/WHEEL
kumparanian-1.2.1.dist-info/entry_points.txt
kumparanian-1.2.1.dist-info/RECORD
