Metadata-Version: 2.3
Name: kumparanian
Version: 1.2.1
Summary: Kumparanian CLI
License: kumparan
Author: Zavli Juwantara
Author-email: zavli.juwantara@kumparan.com
Maintainer: Bayu
Maintainer-email: bayualdiyansyah@gmail.com
Requires-Python: >=3.10,<3.12
Classifier: License :: Other/Proprietary License
Classifier: Programming Language :: Python :: 3
Classifier: Programming Language :: Python :: 3.10
Classifier: Programming Language :: Python :: 3.11
Requires-Dist: click (>=8.1.7,<9.0.0)
Requires-Dist: colorama (>=0.4.6,<0.5.0)
Requires-Dist: dill (==0.3.8)
Requires-Dist: numpy (==1.24.3)
Requires-Dist: scikit-learn (==1.5.1)
Requires-Dist: tensorflow (==2.16.1)
Requires-Dist: tf-keras (==2.16.0)
Requires-Dist: urllib3 (==2.6.0)
Project-URL: Repository, https://github.com/kumparan/kumparanian
